odoo/addons/ssi_rma/README.rst
odoo/addons/ssi_rma/__init__.py
odoo/addons/ssi_rma/__manifest__.py
odoo/addons/ssi_rma/menu.xml
odoo/addons/ssi_rma/data/base_automation_data.xml
odoo/addons/ssi_rma/data/ir_actions_server_data.xml
odoo/addons/ssi_rma/data/ir_sequence_data.xml
odoo/addons/ssi_rma/data/location_type_data.xml
odoo/addons/ssi_rma/data/rma_customer_approval_template_data.xml
odoo/addons/ssi_rma/data/rma_customer_policy_template_data.xml
odoo/addons/ssi_rma/data/rma_policy_data.xml
odoo/addons/ssi_rma/data/rma_policy_field_data.xml
odoo/addons/ssi_rma/data/rma_supplier_approval_template_data.xml
odoo/addons/ssi_rma/data/rma_supplier_policy_template_data.xml
odoo/addons/ssi_rma/data/sequence_template_data.xml
odoo/addons/ssi_rma/data/stock_picking_type_category_data.xml
odoo/addons/ssi_rma/demo/rma_operation_demo.xml
odoo/addons/ssi_rma/demo/rma_route_template_demo.xml
odoo/addons/ssi_rma/demo/stock_location_route_demo.xml
odoo/addons/ssi_rma/i18n/ssi_rma.pot
odoo/addons/ssi_rma/models/__init__.py
odoo/addons/ssi_rma/models/rma_customer.py
odoo/addons/ssi_rma/models/rma_customer_line.py
odoo/addons/ssi_rma/models/rma_line_mixin.py
odoo/addons/ssi_rma/models/rma_mixin.py
odoo/addons/ssi_rma/models/rma_operation.py
odoo/addons/ssi_rma/models/rma_policy.py
odoo/addons/ssi_rma/models/rma_policy_field.py
odoo/addons/ssi_rma/models/rma_policy_rule.py
odoo/addons/ssi_rma/models/rma_reason.py
odoo/addons/ssi_rma/models/rma_route_template.py
odoo/addons/ssi_rma/models/rma_supplier.py
odoo/addons/ssi_rma/models/rma_supplier_line.py
odoo/addons/ssi_rma/models/stock_move.py
odoo/addons/ssi_rma/models/stock_rule.py
odoo/addons/ssi_rma/security/ir.model.access.csv
odoo/addons/ssi_rma/security/ir_module_category_data.xml
odoo/addons/ssi_rma/security/ir_rule_data.xml
odoo/addons/ssi_rma/security/res_group_data.xml
odoo/addons/ssi_rma/static/description/icon.png
odoo/addons/ssi_rma/views/customer_rma_in_views.xml
odoo/addons/ssi_rma/views/customer_rma_out_views.xml
odoo14_addon_ssi_rma-14.0.2.4.0.dist-info/METADATA
odoo14_addon_ssi_rma-14.0.2.4.0.dist-info/WHEEL
odoo14_addon_ssi_rma-14.0.2.4.0.dist-info/top_level.txt
odoo14_addon_ssi_rma-14.0.2.4.0.dist-info/RECORD
